zopflipy-1.11.dist-info/top_level.txt
zopflipy-1.11.dist-info/RECORD
zopflipy-1.11.dist-info/LICENSE.txt
zopflipy-1.11.dist-info/METADATA
zopflipy-1.11.dist-info/WHEEL
zopfli/_zopfli.cpython-39-x86_64-linux-gnu.so
zopfli/__version__.py
zopfli/__init__.py
zopfli/_zopfli.pyi
zopfli/py.typed
